[
  {
    "id": 7997,
    "user_id": "0a2b0d17-7fc6-46b2-9a95-3b1e77cd3a94",
    "first_name": "Joany",
    "last_name": "Hettinger",
    "company": "spring_company",
    "account_num": "ggj32",
    "phone_num": "+1(300)925-5662"
  },
  {
    "id": 1347,
    "user_id": "13e8d7fe-72c9-401e-8ce9-6180caea19ba",
    "first_name": "Lauren",
    "last_name": "Borer",
    "company": "joined_company",
    "account_num": "8srodw",
    "phone_num": "+1(192)766-1469"
  },
  {
    "id": 1468,
    "user_id": "a11ef67d-13ef-40b1-997b-5a4b3244d27d",
    "first_name": "Abelardo",
    "last_name": "Jast",
    "company": "palace_company",
    "account_num": "trz2a",
    "phone_num": "+1(535)836-5175"
  },
  {
    "id": 9380,
    "user_id": "de2c0105-104b-4f40-8fbb-305c3f83e3cb",
    "first_name": "Deonte",
    "last_name": "Hand",
    "company": "exact_company",
    "account_num": "pq8kv",
    "phone_num": "+1(933)397-4014"
  },
  {
    "id": 3204,
    "user_id": "d468fc49-2807-4ffe-ad10-7309602eafb6",
    "first_name": "Aurelia",
    "last_name": "Abshire",
    "company": "contrast_company",
    "account_num": "nt47m8",
    "phone_num": "+1(798)219-2368"
  },
  {
    "id": 1656,
    "user_id": "56025216-aaf6-4b6c-bcc1-4844f059610a",
    "first_name": "Dulce",
    "last_name": "Rodriguez",
    "company": "struggle_company",
    "account_num": "2mypl",
    "phone_num": "+1(450)835-8822"
  },
  {
    "id": 9626,
    "user_id": "6394057c-c6d2-400c-a460-c70a224f3664",
    "first_name": "Derek",
    "last_name": "Kohler",
    "company": "quiet_company",
    "account_num": "69zuyp",
    "phone_num": "+1(519)168-1024"
  },
  {
    "id": 3733,
    "user_id": "4151a4aa-becc-432a-a422-76c74cc5dda4",
    "first_name": "Dan",
    "last_name": "Glover",
    "company": "he_company",
    "account_num": "bpbf37",
    "phone_num": "+1(590)376-4969"
  },
  {
    "id": 4487,
    "user_id": "804e379e-e9b0-4a42-843e-4c08cf5a0bed",
    "first_name": "Antonina",
    "last_name": "Kshlerin",
    "company": "location_company",
    "account_num": "7jzxfm",
    "phone_num": "+1(147)797-3708"
  },
  {
    "id": 7519,
    "user_id": "2e421058-ee40-4e41-a8fb-3a24cd842e18",
    "first_name": "Dale",
    "last_name": "Barrows",
    "company": "voyage_company",
    "account_num": "ssmsi",
    "phone_num": "+1(960)937-3482"
  }
]